poco/__init__.py
poco/poco.py
poco/commands/__init__.py
poco/commands/abstract_command.py
poco/commands/branch.py
poco/commands/branches.py
poco/commands/build.py
poco/commands/catalog.py
poco/commands/catalog_update.py
poco/commands/check_version.py
poco/commands/checkout.py
poco/commands/clean.py
poco/commands/config.py
poco/commands/init.py
poco/commands/install.py
poco/commands/log.py
poco/commands/pack.py
poco/commands/plan.py
poco/commands/project_add.py
poco/commands/project_init.py
poco/commands/project_ls.py
poco/commands/project_remove.py
poco/commands/ps.py
poco/commands/pull.py
poco/commands/repo_add.py
poco/commands/repo_branch.py
poco/commands/repo_branches.py
poco/commands/repo_ls.py
poco/commands/repo_pull.py
poco/commands/repo_push.py
poco/commands/repo_remove.py
poco/commands/restart.py
poco/commands/start.py
poco/commands/stop.py
poco/commands/unpack.py
poco/services/__init__.py
poco/services/abstract_repository.py
poco/services/bitbucket_repository.py
poco/services/catalog_handler.py
poco/services/command_handler.py
poco/services/command_runners.py
poco/services/compose_handler.py
poco/services/config_handler.py
poco/services/console_logger.py
poco/services/cta_utils.py
poco/services/environment_utils.py
poco/services/file_repository.py
poco/services/file_utils.py
poco/services/git_repository.py
poco/services/github_repository.py
poco/services/gitlab_repository.py
poco/services/package_handler.py
poco/services/project_utils.py
poco/services/state.py
poco/services/state_utils.py
poco/services/svn_repository.py
poco/services/yaml_utils.py
poco/services/resources/__init__.py
poco/services/resources/command-hierarchy.yml
poco/services/resources/docker-compose.yml
poco/services/resources/poco.yml
poco/tests/__init__.py
poco/tests/abstract_test.py
poco/tests/clean_mock_test.py
poco/tests/poco_test.py
poco/tests/up_mock_test.py
poco/tests/versions_test.py
poco-0.99.3.dist-info/licenses/LICENCE
poco-0.99.3.dist-info/METADATA
poco-0.99.3.dist-info/WHEEL
poco-0.99.3.dist-info/entry_points.txt
poco-0.99.3.dist-info/top_level.txt
poco-0.99.3.dist-info/RECORD
