Metadata-Version: 2.4
Name: poco
Version: 0.99.3
Summary: poco lets you catalogue and manage your Docker projects using simple YAML files to shorten the route from finding your project to initialising it in your environment.
Home-page: https://www.shiwaforce.com
Author: Shiwaforce.com
License: Apache License 2.0
Classifier: Development Status :: 4 - Beta
Classifier: Intended Audience :: Developers
Classifier: Intended Audience :: System Administrators
Classifier: Natural Language :: English
Classifier: License :: OSI Approved :: Apache Software License
Classifier: Programming Language :: Python
Classifier: Programming Language :: Python :: 3
Classifier: Programming Language :: Python :: 3.7
Classifier: Programming Language :: Python :: 3.8
Classifier: Programming Language :: Python :: 3.9
Classifier: Programming Language :: Python :: 3.10
License-File: LICENCE
Requires-Dist: PyYAML==6.0.1
Requires-Dist: pyaml==21.10.1
Requires-Dist: gitpython==3.1.30
Requires-Dist: svn==1.0.1
Requires-Dist: docopt==0.6.2
Requires-Dist: pygithub==1.55
Requires-Dist: python-gitlab==3.9.0
Requires-Dist: packaging==21.3
Dynamic: author
Dynamic: classifier
Dynamic: description
Dynamic: description-content-type
Dynamic: home-page
Dynamic: license
Dynamic: license-file
Dynamic: requires-dist
Dynamic: summary
